libservice/__init__.py
libservice/addr.py
libservice/asset.py
libservice/check.py
libservice/exceptions.py
libservice/logger.py
libservice/loop.py
libservice/serviceroom.py
libservice/severity.py
libservice/start.py
libservice/utils.py
libservice/hub/__init__.py
libservice/hub/client.py
libservice/hub/protocol.py
libservice/hub/net/__init__.py
libservice/hub/net/package.py
libservice/hub/net/protocol.py
libservice/ticonn/__init__.py
libservice/ticonn/ticonn.py
libservice-1.0.3.dist-info/licenses/LICENSE
libservice-1.0.3.dist-info/METADATA
libservice-1.0.3.dist-info/WHEEL
libservice-1.0.3.dist-info/top_level.txt
libservice-1.0.3.dist-info/RECORD
