Metadata-Version: 2.4
Name: libservice
Version: 1.0.3
Summary: Library for building InfraSonar services
Home-page: https://github.com/infrasonar/python-libservice
Download-URL: https://github.com/infrasonar/python-libservice/tarball/v1.0.3
Author: Cesbit
Author-email: info@cesbit.com
Keywords: monitoring,infrasonar,service
Classifier: Intended Audience :: Developers
Classifier: Operating System :: OS Independent
Classifier: Programming Language :: Python :: 3.7
Classifier: Programming Language :: Python :: 3.8
Classifier: Programming Language :: Python :: 3.9
Classifier: Programming Language :: Python :: 3.10
Classifier: Programming Language :: Python :: 3 :: Only
Classifier: Topic :: Software Development :: Libraries :: Python Modules
Classifier: Topic :: Text Processing :: Linguistic
License-File: LICENSE
Requires-Dist: colorlog
Requires-Dist: cryptography
Requires-Dist: msgpack
Requires-Dist: python-thingsdb
Dynamic: author
Dynamic: author-email
Dynamic: classifier
Dynamic: description
Dynamic: description-content-type
Dynamic: download-url
Dynamic: home-page
Dynamic: keywords
Dynamic: license-file
Dynamic: requires-dist
Dynamic: summary
